<?xml version='1.0'?>
<CARD_V2>
  <FILENAME text="BLOODTHRONE_VAMPIRE_M13_083" />
  <CARDNAME text="BLOODTHRONE_VAMPIRE" />
  <TITLE>
    <LOCALISED_TEXT LanguageCode="en-US"><![CDATA[Bloodthrone Vampire]]></LOCALISED_TEXT>
    <LOCALISED_TEXT LanguageCode="de-DE"><![CDATA[Blutthron-Vampir]]></LOCALISED_TEXT>
    <LOCALISED_TEXT LanguageCode="es-ES"><![CDATA[Vampiro del trono sangriento]]></LOCALISED_TEXT>
    <LOCALISED_TEXT LanguageCode="fr-FR"><![CDATA[Vampire du trône de sang]]></LOCALISED_TEXT>
    <LOCALISED_TEXT LanguageCode="it-IT"><![CDATA[Vampira del Trono Insanguinato]]></LOCALISED_TEXT>
    <LOCALISED_TEXT LanguageCode="jp-JA"><![CDATA[血の座の吸血鬼]]></LOCALISED_TEXT>
    <LOCALISED_TEXT LanguageCode="ko-KR"><![CDATA[피묻은 왕좌의 흡혈귀]]></LOCALISED_TEXT>
    <LOCALISED_TEXT LanguageCode="ru-RU"><![CDATA[Вампир Кровавого Престола]]></LOCALISED_TEXT>
    <LOCALISED_TEXT LanguageCode="pt-BR"><![CDATA[Vampiro do Sangue Real]]></LOCALISED_TEXT>
  </TITLE>
  <MULTIVERSEID value="M13_083" />
  <ARTID value="M13_083" />
  <ARTIST name="Steve Argyle" />
  <CASTING_COST cost="{1}{B}" />
  <FLAVOURTEXT>
    <LOCALISED_TEXT LanguageCode="en-US"><![CDATA[“What I need is your blood. What I don’t need is your permission.”]]></LOCALISED_TEXT>
    <LOCALISED_TEXT LanguageCode="de-DE"><![CDATA[„Was ich brauche, ist Blut. Was ich nicht brauche, ist deine Erlaubnis."]]></LOCALISED_TEXT>
    <LOCALISED_TEXT LanguageCode="es-ES"><![CDATA["Lo que necesito es tu sangre. Lo que no necesito es tu permiso."]]></LOCALISED_TEXT>
    <LOCALISED_TEXT LanguageCode="fr-FR"><![CDATA[« J'ai besoin de votre sang. Pas de votre permission. »]]></LOCALISED_TEXT>
    <LOCALISED_TEXT LanguageCode="it-IT"><![CDATA["Quello di cui ho bisogno è il tuo sangue, non il tuo permesso di prendermelo."]]></LOCALISED_TEXT>
    <LOCALISED_TEXT LanguageCode="jp-JA"><![CDATA[「私に必要なのはお前の血だ。お前の許可など求めておらぬ。」]]></LOCALISED_TEXT>
    <LOCALISED_TEXT LanguageCode="ko-KR"><![CDATA["난 너의 피가 필요할 뿐, 너의 허락 따위는 필요 없다."]]></LOCALISED_TEXT>
    <LOCALISED_TEXT LanguageCode="ru-RU"><![CDATA[«Что мне нужно, так это твоя кровь. Что мне совсем не нужно, так это твое разрешение».]]></LOCALISED_TEXT>
    <LOCALISED_TEXT LanguageCode="pt-BR"><![CDATA["O que eu preciso é do seu sangue. O que eu não preciso é da sua permissão."]]></LOCALISED_TEXT>
  </FLAVOURTEXT>
  <TYPE metaname="Creature" />
  <SUB_TYPE metaname="Vampire" />
  <EXPANSION value="M13" />
  <RARITY metaname="C" />
  <POWER value="1" />
  <TOUGHNESS value="1" />
  <ACTIVATED_ABILITY filter_zone="ZONE_IN_PLAY">
    <LOCALISED_TEXT LanguageCode="en-US"><![CDATA[Sacrifice a creature: Bloodthrone Vampire gets +2/+2 until end of turn.]]></LOCALISED_TEXT>
    <LOCALISED_TEXT LanguageCode="de-DE"><![CDATA[Opfere eine Kreatur: Der Blutthron-Vampir erhält +2/+2 bis zum Ende des Zuges.]]></LOCALISED_TEXT>
    <LOCALISED_TEXT LanguageCode="es-ES"><![CDATA[Sacrificar una criatura: La Vampiro del trono sangriento obtiene +2/+2 hasta el final del turno.]]></LOCALISED_TEXT>
    <LOCALISED_TEXT LanguageCode="fr-FR"><![CDATA[Sacrifiez une créature : La Vampire du trône de sang gagne +2/+2 jusqu'à la fin du tour.]]></LOCALISED_TEXT>
    <LOCALISED_TEXT LanguageCode="it-IT"><![CDATA[Sacrifica una creatura: La Vampira del Trono Insanguinato prende +2/+2 fino alla fine del turno.]]></LOCALISED_TEXT>
    <LOCALISED_TEXT LanguageCode="jp-JA"><![CDATA[クリーチャーを１体生け贄に捧げる：血の座の吸血鬼は、ターン終了時まで＋２/＋２の修整を受ける。]]></LOCALISED_TEXT>
    <LOCALISED_TEXT LanguageCode="ko-KR"><![CDATA[생물 한 개를 희생한다: 피묻은 왕좌의 흡혈귀는 턴종료까지 +2/+2를 받는다.]]></LOCALISED_TEXT>
    <LOCALISED_TEXT LanguageCode="ru-RU"><![CDATA[Пожертвуйте существо: Вампир Кровавого Престола получает +2/+2 до конца хода.]]></LOCALISED_TEXT>
    <LOCALISED_TEXT LanguageCode="pt-BR"><![CDATA[Sacrifique uma criatura: Vampiro do Sangue Real recebe +2/+2 até o final do turno.]]></LOCALISED_TEXT>
	<COST type="Sacrifice">
      <TARGET_DEFINITION id="6">
      local filter = Object():GetFilter()
      filter:Clear()
      filter:AddCardType( CARD_TYPE_CREATURE )
      filter:SetPlayer( EffectController() )
      filter:SetZone( ZONE_IN_PLAY )
      filter:SetHint( HINT_ENEMY, EffectController() )
      filter:NotTargetted()
      </TARGET_DEFINITION>
      <TARGET_DETERMINATION>
      return AtLeastOneTargetFromDefinition(6)
      </TARGET_DETERMINATION>
      <PLAYTIME>
      EffectController():ChooseTarget( 6, "CARD_QUERY_CHOOSE_CREATURE_TO_SACRIFICE", EffectDC():Make_Targets(0) )
      </PLAYTIME></COST>
	<CONTINUOUS_ACTION layer="7C">
    if EffectSource() ~= nil then
    	EffectSource():GetCurrentCharacteristics():Power_Add( 2 )
    	EffectSource():GetCurrentCharacteristics():Toughness_Add( 2 )
    end
    </CONTINUOUS_ACTION>
    <DURATION simple_duration="UntilEOT" />
	<AI_AVAILABILITY step="declare_blockers" />
    <AI_AVAILABILITY type="in_response_dangerous" />
  </ACTIVATED_ABILITY>
  <SFX text="COMBAT_FANG_LARGE_ATTACK" power_boundary_min="4" power_boundary_max="-1" />
  <SFX text="COMBAT_FANG_SMALL_ATTACK" power_boundary_min="1" power_boundary_max="3" />
  <AI_BASE_SCORE score="400" zone="ZONE_IN_PLAY" />
</CARD_V2>
