<UNLOCKS uid="8933" deck_uid="893" content_pack="0" game_mode="2">
  <CARD name="DRANA_KALASTRIA_BLOODCHIEF_276905#" deckOrderId="70" unlockOrderId="0" quantity="1" />
  <CARD name="MITOTIC_SLIME_276952#" deckOrderId="71" unlockOrderId="1" quantity="1" />
  <CARD name="GO_FOR_THE_THROAT_277128#" deckOrderId="72" unlockOrderId="2" quantity="1" />
  <CARD name="DEFENSE_OF_THE_HEART_277341#" deckOrderId="73" unlockOrderId="3" quantity="1" />
  <CARD name="RANCOR_276969#" deckOrderId="74" unlockOrderId="4" quantity="1" />
  <CARD name="TROLL_ASCETIC_276840#" deckOrderId="75" unlockOrderId="5" quantity="1" />
  <CARD name="CABAL_PATRIARCH_277191#" deckOrderId="76" unlockOrderId="6" quantity="1" />
  <CARD name="CONSUMING_VAPORS_277252#" deckOrderId="77" unlockOrderId="7" quantity="1" />
  <CARD name="PERNICIOUS_DEED_276738#" deckOrderId="78" unlockOrderId="8" quantity="1" />
  <CARD name="DAMNATION_276893#" deckOrderId="79" unlockOrderId="9" quantity="1" />
</UNLOCKS>