<?xml version='1.0'?>
<CARD_V2>
  <FILENAME text="GLISTENER_ELF_248294" />
  <CARDNAME text="GLISTENER_ELF" />
  <TITLE>
    <LOCALISED_TEXT LanguageCode="en-US"><![CDATA[Glistener Elf]]></LOCALISED_TEXT>
    <LOCALISED_TEXT LanguageCode="it-IT"><![CDATA[Elfa Scintillante]]></LOCALISED_TEXT>
    <LOCALISED_TEXT LanguageCode="de-DE"><![CDATA[Glitzernde Elfin]]></LOCALISED_TEXT>
    <LOCALISED_TEXT LanguageCode="fr-FR"><![CDATA[Elfe luisant]]></LOCALISED_TEXT>
    <LOCALISED_TEXT LanguageCode="es-ES"><![CDATA[Elfo iridiscente]]></LOCALISED_TEXT>
    <LOCALISED_TEXT LanguageCode="jp-JA"><![CDATA[ぎらつかせのエルフ]]></LOCALISED_TEXT>
    <LOCALISED_TEXT LanguageCode="ko-KR"><![CDATA[Glistener Elf]]></LOCALISED_TEXT>
    <LOCALISED_TEXT LanguageCode="ru-RU"><![CDATA[Эльф-Умаслитель]]></LOCALISED_TEXT>
    <LOCALISED_TEXT LanguageCode="pt-BR"><![CDATA[Elfo Brilhante]]></LOCALISED_TEXT>
  </TITLE>
  <MULTIVERSEID value="248294" />
  <ARTID value="888248294" />
  <ARTIST name="Steve Argyle" />
  <CASTING_COST cost="{G}" />
  <FLAVOURTEXT>
    <LOCALISED_TEXT LanguageCode="en-US"><![CDATA[“Beg me for life, and I will fill you with the glory of Phyrexian perfection.”]]></LOCALISED_TEXT>
    <LOCALISED_TEXT LanguageCode="it-IT"><![CDATA[“Supplicami di lasciarti vivere e ti riempirò con la gloria della perfezione di Phyrexia.”]]></LOCALISED_TEXT>
    <LOCALISED_TEXT LanguageCode="de-DE"><![CDATA[„Bettele um dein Leben, und ich werde dich mit dem Ruhm der phyrexianischen Perfektion erfüllen.”]]></LOCALISED_TEXT>
    <LOCALISED_TEXT LanguageCode="fr-FR"><![CDATA[« Suppliez-moi d’épargner votre vie, et je vous emplirai de la gloire de la perfection phyrexiane. »]]></LOCALISED_TEXT>
    <LOCALISED_TEXT LanguageCode="es-ES"><![CDATA[“Ruega por tu vida y te mejoraré con la perfección pirexiana.”]]></LOCALISED_TEXT>
    <LOCALISED_TEXT LanguageCode="jp-JA"><![CDATA[「命を乞うがいい。さすればお前をファイレクシアの完成の栄光で満たしてやろう。」]]></LOCALISED_TEXT>
    <LOCALISED_TEXT LanguageCode="ko-KR"><![CDATA[“Beg me for life, and I will fill you with the glory of Phyrexian perfection.”]]></LOCALISED_TEXT>
    <LOCALISED_TEXT LanguageCode="ru-RU"><![CDATA[«Умоляй меня сохранить тебе жизнь, и я наполню тебя фирексийским совершенством».]]></LOCALISED_TEXT>
    <LOCALISED_TEXT LanguageCode="pt-BR"><![CDATA[“Implore-me pela vida e eu o preencherei com a glória da perfeição phyrexiana.”]]></LOCALISED_TEXT>
  </FLAVOURTEXT>
  <TYPE metaname="Creature" />
  <SUB_TYPE metaname="Elf" order_de-DE="0" order_es-ES="1" order_fr-FR="0" order_it-IT="1" order_jp-JA="0" order_ko-KR="0" order_pt-BR="0" order_ru-RU="0" />
  <SUB_TYPE metaname="Warrior" order_de-DE="1" order_es-ES="0" order_fr-FR="1" order_it-IT="0" order_jp-JA="1" order_ko-KR="1" order_pt-BR="1" order_ru-RU="1" />
  <EXPANSION value="NPH" />
  <RARITY metaname="C" />
  <POWER value="1" />
  <TOUGHNESS value="1" />
  <STATIC_ABILITY>
    <LOCALISED_TEXT LanguageCode="en-US"><![CDATA[Infect]]></LOCALISED_TEXT>
    <LOCALISED_TEXT LanguageCode="it-IT"><![CDATA[Infettare]]></LOCALISED_TEXT>
    <LOCALISED_TEXT LanguageCode="de-DE"><![CDATA[Infizieren]]></LOCALISED_TEXT>
    <LOCALISED_TEXT LanguageCode="fr-FR"><![CDATA[Infection]]></LOCALISED_TEXT>
    <LOCALISED_TEXT LanguageCode="es-ES"><![CDATA[Infectar.]]></LOCALISED_TEXT>
    <LOCALISED_TEXT LanguageCode="jp-JA"><![CDATA[感染]]></LOCALISED_TEXT>
    <LOCALISED_TEXT LanguageCode="ko-KR"><![CDATA[Infect]]></LOCALISED_TEXT>
    <LOCALISED_TEXT LanguageCode="ru-RU"><![CDATA[Инфекция]]></LOCALISED_TEXT>
    <LOCALISED_TEXT LanguageCode="pt-BR"><![CDATA[Infectar]]></LOCALISED_TEXT>
    <CONTINUOUS_ACTION>
    local characteristics = Object():GetCurrentCharacteristics()
    characteristics:Characteristic_Set( CHARACTERISTIC_INFECT, 1 )
    </CONTINUOUS_ACTION>
  </STATIC_ABILITY>
  <HELP title="MORE_INFO_BADGE_TITLE_31" body="MORE_INFO_BADGE_BODY_31" zone="ZONE_ANY" />
  <SFX text="COMBAT_BLADE_LARGE_ATTACK" power_boundary_min="4" power_boundary_max="-1" />
  <SFX text="COMBAT_BLADE_SMALL_ATTACK" power_boundary_min="1" power_boundary_max="3" />
</CARD_V2>