<?xml version='1.0'?>
<CARD_V2>
  <FILENAME text="FLYING_MEN_107291" />
  <CARDNAME text="FLYING_MEN" />
  <TITLE>
    <LOCALISED_TEXT LanguageCode="en-US"><![CDATA[Flying Men]]></LOCALISED_TEXT>
    <LOCALISED_TEXT LanguageCode="it-IT"><![CDATA[Uomini Volanti]]></LOCALISED_TEXT>
    <LOCALISED_TEXT LanguageCode="de-DE"><![CDATA[Fliegende Männer]]></LOCALISED_TEXT>
    <LOCALISED_TEXT LanguageCode="fr-FR"><![CDATA[Hommes volants]]></LOCALISED_TEXT>
    <LOCALISED_TEXT LanguageCode="es-ES"><![CDATA[Hombres voladores]]></LOCALISED_TEXT>
    <LOCALISED_TEXT LanguageCode="jp-JA"><![CDATA[空飛ぶ男]]></LOCALISED_TEXT>
    <LOCALISED_TEXT LanguageCode="ko-KR"><![CDATA[Flying Men]]></LOCALISED_TEXT>
    <LOCALISED_TEXT LanguageCode="ru-RU"><![CDATA[Летун]]></LOCALISED_TEXT>
    <LOCALISED_TEXT LanguageCode="pt-BR"><![CDATA[Homens Voadores]]></LOCALISED_TEXT>
  </TITLE>
  <MULTIVERSEID value="107291" />
  <ARTID value="888107291" />
  <ARTIST name="Christopher Rush" />
  <CASTING_COST cost="{U}" />
  <FLAVOURTEXT>
    <LOCALISED_TEXT LanguageCode="en-US"><![CDATA[Saffiyah clapped her hands and twenty flying men appeared at her side, each well trained in the art of combat.]]></LOCALISED_TEXT>
    <LOCALISED_TEXT LanguageCode="it-IT"><![CDATA[Saffiyah batté le mani e al suo fianco apparvero venti uomini volanti, ciascuno ben addestrato nell'arte del combattimento.]]></LOCALISED_TEXT>
    <LOCALISED_TEXT LanguageCode="de-DE"><![CDATA[Safiyyah klatschte in die Hände, und wie aus dem Nichts erschienen zwanzig fliegende Männer, die alle in der Kunst des Kämpfens ausgebildet waren.]]></LOCALISED_TEXT>
    <LOCALISED_TEXT LanguageCode="fr-FR"><![CDATA[Saffiyah frappa dans ses mains et vingt hommes volants apparurent à ses côtés, tous adeptes de l'art du combat.]]></LOCALISED_TEXT>
    <LOCALISED_TEXT LanguageCode="es-ES"><![CDATA[Saffiyah aplaudió y veinte hombres voladores aparecieron a su lado, todos bien entrenados en el arte del combate.]]></LOCALISED_TEXT>
    <LOCALISED_TEXT LanguageCode="jp-JA"><![CDATA[サフィヤーが手を叩くと、二十人の戦いに長けた空飛ぶ男達が彼女の傍らに並んだ。]]></LOCALISED_TEXT>
    <LOCALISED_TEXT LanguageCode="ko-KR"><![CDATA[Saffiyah clapped her hands and twenty flying men appeared at her side, each well trained in the art of combat.]]></LOCALISED_TEXT>
    <LOCALISED_TEXT LanguageCode="ru-RU"><![CDATA[Саффия хлопнула в ладоши, и двадцать летунов появились рядом с ней — все отличные воины.]]></LOCALISED_TEXT>
    <LOCALISED_TEXT LanguageCode="pt-BR"><![CDATA[Saffiyah bateu palmas e vinte homens voadores apareceram ao seu lado, todos bem treinados na arte do combate.]]></LOCALISED_TEXT>
  </FLAVOURTEXT>
  <TYPE metaname="Creature" />
  <SUB_TYPE metaname="Human" order_de-DE="0" order_es-ES="0" order_fr-FR="0" order_it-IT="0" order_jp-JA="0" order_ko-KR="0" order_pt-BR="0" order_ru-RU="0" />
  <EXPANSION value="DPG" />
  <RARITY metaname="P" />
  <POWER value="1" />
  <TOUGHNESS value="1" />
  <STATIC_ABILITY>
    <LOCALISED_TEXT LanguageCode="en-US"><![CDATA[Flying]]></LOCALISED_TEXT>
    <LOCALISED_TEXT LanguageCode="it-IT"><![CDATA[Volare]]></LOCALISED_TEXT>
    <LOCALISED_TEXT LanguageCode="de-DE"><![CDATA[Fliegend]]></LOCALISED_TEXT>
    <LOCALISED_TEXT LanguageCode="fr-FR"><![CDATA[Vol]]></LOCALISED_TEXT>
    <LOCALISED_TEXT LanguageCode="es-ES"><![CDATA[Vuela.]]></LOCALISED_TEXT>
    <LOCALISED_TEXT LanguageCode="jp-JA"><![CDATA[飛行]]></LOCALISED_TEXT>
    <LOCALISED_TEXT LanguageCode="ko-KR"><![CDATA[Flying]]></LOCALISED_TEXT>
    <LOCALISED_TEXT LanguageCode="ru-RU"><![CDATA[Полет]]></LOCALISED_TEXT>
    <LOCALISED_TEXT LanguageCode="pt-BR"><![CDATA[Voar]]></LOCALISED_TEXT>
    <CONTINUOUS_ACTION>
    local characteristics = Object():GetCurrentCharacteristics()
    characteristics:Characteristic_Set( CHARACTERISTIC_FLYING, 1 )
    </CONTINUOUS_ACTION>
  </STATIC_ABILITY>
</CARD_V2>
